email_draft_generator/__init__.py
email_draft_generator/__main__.py
email_draft_generator/attachment.py
email_draft_generator/email_drafter.py
email_draft_generator/email_list.py
email_draft_generator/email_template.py
email_draft_generator/gmail.py
email_draft_generator/main.py
email_draft_generator/file_parser/__init__.py
email_draft_generator/file_parser/__main__.py
email_draft_generator/file_parser/csv_parser.py
email_draft_generator/file_parser/main.py
email_draft_generator/file_parser/text_parser.py
email_draft_generator/gui/__init__.py
email_draft_generator/gui/__main__.py
email_draft_generator/gui/gmail_gui.py
email_draft_generator/gui/main.py
email_draft_generator/gui/template_editor.py
email_draft_generator/gui/util.py
email_draft_generator-0.1.2.dist-info/METADATA
email_draft_generator-0.1.2.dist-info/WHEEL
email_draft_generator-0.1.2.dist-info/entry_points.txt
email_draft_generator-0.1.2.dist-info/licenses/LICENSE
email_draft_generator-0.1.2.dist-info/RECORD
