Metadata-Version: 2.3
Name: email_draft_generator
Version: 0.1.2
Summary: A utility to generate E-mail drafts from a list of E-mail addresses.
Project-URL: Homepage, https://github.com/CoffeeCoder1/Email-Generator
Project-URL: Bug Reports, https://github.com/CoffeeCoder1/Email-Generator/issues
Project-URL: Source, https://github.com/CoffeeCoder1/Email-Generator
Author-email: Brandon Clague <94200657+fodfodfod@users.noreply.github.com>, Max Nargang <CoffeeCoder1@outlook.com>
Maintainer-email: Max Nargang <CoffeeCoder1@outlook.com>
License: MIT License
License-File: LICENSE
Keywords: email,email-generator,email-template,gmail
Classifier: Development Status :: 4 - Beta
Classifier: Intended Audience :: Customer Service
Classifier: License :: OSI Approved :: MIT License
Classifier: Programming Language :: Python :: 3
Classifier: Topic :: Communications :: Email :: Mailing List Servers
Requires-Python: >=3.10
Requires-Dist: google-api-python-client
Requires-Dist: google-auth-httplib2
Requires-Dist: google-auth-oauthlib
Requires-Dist: json-fix
Provides-Extra: packaging
Requires-Dist: pillow; extra == 'packaging'
Requires-Dist: pyinstaller; extra == 'packaging'
